lang111-0.1.0.dist-info/licenses/LICENSE
satya/__init__.py
satya/core.py
lang111-0.1.0.dist-info/METADATA
lang111-0.1.0.dist-info/WHEEL
lang111-0.1.0.dist-info/top_level.txt
lang111-0.1.0.dist-info/RECORD
