Metadata-Version: 2.4
Name: lang111
Version: 0.1.0
Summary: A natural language interpreter for data structures and algorithms
Home-page: https://github.com/satya/satya-language
Author: Satya
Author-email: satya@example.com
Keywords: data structures,algorithms,natural language,education
Classifier: Programming Language :: Python :: 3
Classifier: License :: OSI Approved :: MIT License
Classifier: Operating System :: OS Independent
Classifier: Development Status :: 4 - Beta
Classifier: Intended Audience :: Developers
Classifier: Intended Audience :: Education
Classifier: Topic :: Software Development :: Libraries
Classifier: Topic :: Education
Requires-Python: >=3.6
License-File: LICENSE
Dynamic: author
Dynamic: author-email
Dynamic: classifier
Dynamic: description
Dynamic: description-content-type
Dynamic: home-page
Dynamic: keywords
Dynamic: license-file
Dynamic: requires-python
Dynamic: summary
